pyshred/__init__.py
pyshred/engine/__init__.py
pyshred/engine/engine.py
pyshred/engine/parametric_engine.py
pyshred/models/__init__.py
pyshred/models/_sindy.py
pyshred/models/_sindy_utils.py
pyshred/models/shred.py
pyshred/models/decoder_models/__init__.py
pyshred/models/decoder_models/abstract_decoder.py
pyshred/models/decoder_models/mlp_model.py
pyshred/models/decoder_models/unet_model.py
pyshred/models/latent_forecaster_models/__init__.py
pyshred/models/latent_forecaster_models/abstract_latent_forecaster.py
pyshred/models/latent_forecaster_models/lstm.py
pyshred/models/latent_forecaster_models/sindy.py
pyshred/models/sequence_models/__init__.py
pyshred/models/sequence_models/abstract_sequence.py
pyshred/models/sequence_models/gru_model.py
pyshred/models/sequence_models/lstm_model.py
pyshred/models/sequence_models/transformer_model.py
pyshred/objects/__init__.py
pyshred/objects/dataset.py
pyshred/objects/device.py
pyshred/objects/sindy.py
pyshred/processor/__init__.py
pyshred/processor/data_manager.py
pyshred/processor/parametric_data_manager.py
pyshred/processor/utils.py
pyshred-1.0.21.dist-info/licenses/LICENSE
pyshred-1.0.21.dist-info/METADATA
pyshred-1.0.21.dist-info/WHEEL
pyshred-1.0.21.dist-info/top_level.txt
pyshred-1.0.21.dist-info/RECORD
