Metadata-Version: 2.4
Name: pyshred
Version: 1.0.21
Summary: PySHRED: Package for Shallow Recurrent Decoding
Author: David Ye, Jan Williams, Mars Gao, Matteo Tomasetto, Stefano Riva, Nathan Kutz
Author-email: pyshred1@gmail.com
License: MIT
Classifier: Programming Language :: Python :: 3
Classifier: License :: OSI Approved :: MIT License
Classifier: Operating System :: OS Independent
Requires-Python: >=3.8
License-File: LICENSE
Requires-Dist: pysindy
Requires-Dist: numpy<2.0
Requires-Dist: scikit-learn
Requires-Dist: pandas
Requires-Dist: torch
Dynamic: author
Dynamic: author-email
Dynamic: classifier
Dynamic: description
Dynamic: description-content-type
Dynamic: license
Dynamic: license-file
Dynamic: requires-dist
Dynamic: requires-python
Dynamic: summary
